pushbullet/__init__.py
pushbullet/__version__.py
pushbullet/_compat.py
pushbullet/channel.py
pushbullet/chat.py
pushbullet/device.py
pushbullet/errors.py
pushbullet/filetype.py
pushbullet/helpers.py
pushbullet/listener.py
pushbullet/pushbullet.py
pushbullet.py-0.11.2.dist-info/LICENSE
pushbullet.py-0.11.2.dist-info/METADATA
pushbullet.py-0.11.2.dist-info/WHEEL
pushbullet.py-0.11.2.dist-info/top_level.txt
pushbullet.py-0.11.2.dist-info/RECORD
